trelis_openai_logger/__init__.py
trelis_openai_logger/db.py
trelis_openai_logger/models.py
trelis_openai_logger/patch.py
trelis_openai_logger-1.0.0.dist-info/METADATA
trelis_openai_logger-1.0.0.dist-info/WHEEL
trelis_openai_logger-1.0.0.dist-info/licenses/LICENSE
trelis_openai_logger-1.0.0.dist-info/RECORD
