Metadata-Version: 2.4
Name: trelis-openai-logger
Version: 1.0.0
Summary: PostgreSQL logger for OpenAI-style LLM API interactions
Author-email: Trelis Research <hello@trelis.com>
License-File: LICENSE
Keywords: llm,logging,monitoring,openai,postgresql
Classifier: Development Status :: 4 - Beta
Classifier: Intended Audience :: Developers
Classifier: Programming Language :: Python :: 3
Classifier: Programming Language :: Python :: 3.8
Classifier: Programming Language :: Python :: 3.9
Classifier: Programming Language :: Python :: 3.10
Classifier: Programming Language :: Python :: 3.11
Classifier: Programming Language :: Python :: 3.12
Classifier: Topic :: Software Development :: Libraries :: Python Modules
Requires-Python: >=3.8
Requires-Dist: asyncpg<1,>=0.29
Requires-Dist: openai>=1.25.0
Requires-Dist: psycopg2-binary>=2.9.0
Requires-Dist: pydantic>=2.0.0
Requires-Dist: python-dotenv>=1.0.0
Requires-Dist: sqlalchemy>=2.0.0
